README.md
setup.py
nans_e_puzzle_bfs.egg-info/PKG-INFO
nans_e_puzzle_bfs.egg-info/SOURCES.txt
nans_e_puzzle_bfs.egg-info/dependency_links.txt
nans_e_puzzle_bfs.egg-info/top_level.txt
source/__init__.py
source/puzzleBFS.py