Metadata-Version: 2.1
Name: nans-e-puzzle-bfs
Version: 0.0.1
Summary: A Example of solwing eight puzzle using BFS(Breadth first Search)
Home-page: UNKNOWN
Author: Narendra
Author-email: narendra02031997@gmail.com
License: UNKNOWN
Platform: UNKNOWN
Classifier: Programming Language :: Python :: 3
Classifier: License :: OSI Approved :: MIT License
Classifier: Operating System :: OS Independent
